liquidata.py
liquidata-0.1.1.dist-info/LICENSE
liquidata-0.1.1.dist-info/WHEEL
liquidata-0.1.1.dist-info/METADATA
liquidata-0.1.1.dist-info/RECORD
