Metadata-Version: 2.1
Name: liquidata
Version: 0.1.1
Summary: EDSL for data pipelines in Python
Home-page: https://github.com/jacg/liquidata
License: MIT
Author: Jacek Generowicz
Author-email: github@my-post-office.net
Requires-Python: >=3.6,<4.0
Classifier: License :: OSI Approved :: MIT License
Classifier: Programming Language :: Python :: 3
Classifier: Programming Language :: Python :: 3.6
Classifier: Programming Language :: Python :: 3.7
Classifier: Programming Language :: Python :: 3.8
Project-URL: Documentation, https://jacg.github.io/liquidata/
Project-URL: Repository, https://github.com/jacg/liquidata
